{
  "emoji_list": [
    {
      "name": "sv128629",
      "unicode": 128629
    },
    {
      "name": "sv128630",
      "unicode": 128630
    },
    {
      "name": "sv128604",
      "unicode": 128604
    },
    {
      "name": "sv128605",
      "unicode": 128605
    },
    {
      "name": "sv128606",
      "unicode": 128606
    },
    {
      "name": "sv128607",
      "unicode": 128607
    },
    {
      "name": "sv128608",
      "unicode": 128608
    },
    {
      "name": "sv128609",
      "unicode": 128609
    },
    {
      "name": "sv128610",
      "unicode": 128610
    },
    {
      "name": "sv128611",
      "unicode": 128611
    },
    {
      "name": "sv128612",
      "unicode": 128612
    },
    {
      "name": "sv128613",
      "unicode": 128613
    },
    {
      "name": "sv128614",
      "unicode": 128614
    },
    {
      "name": "sv128615",
      "unicode": 128615
    },
    {
      "name": "sv128616",
      "unicode": 128616
    },
    {
      "name": "sv128617",
      "unicode": 128617
    },
    {
      "name": "sv128618",
      "unicode": 128618
    },
    {
      "name": "sv128619",
      "unicode": 128619
    },
    {
      "name": "sv128620",
      "unicode": 128620
    },
    {
      "name": "sv128621",
      "unicode": 128621
    },
    {
      "name": "sv128622",
      "unicode": 128622
    },
    {
      "name": "sv128623",
      "unicode": 128623
    },
    {
      "name": "sv128624",
      "unicode": 128624
    },
    {
      "name": "sv128625",
      "unicode": 128625
    },
    {
      "name": "sv128626",
      "unicode": 128626
    },
    {
      "name": "sv128627",
      "unicode": 128627
    },
    {
      "name": "sv128628",
      "unicode": 128628
    }

  ]
}
